amp_rsl_rl/__init__.py
amp_rsl_rl/algorithms/__init__.py
amp_rsl_rl/algorithms/amp_ppo.py
amp_rsl_rl/networks/__init__.py
amp_rsl_rl/networks/ac_moe.py
amp_rsl_rl/networks/discriminator.py
amp_rsl_rl/runners/__init__.py
amp_rsl_rl/runners/amp_on_policy_runner.py
amp_rsl_rl/storage/__init__.py
amp_rsl_rl/storage/replay_buffer.py
amp_rsl_rl/utils/__init__.py
amp_rsl_rl/utils/exporter.py
amp_rsl_rl/utils/motion_loader.py
amp_rsl_rl/utils/wandb_utils.py
amp_rsl_rl-1.1.1.dist-info/licenses/LICENSE
amp_rsl_rl-1.1.1.dist-info/METADATA
amp_rsl_rl-1.1.1.dist-info/WHEEL
amp_rsl_rl-1.1.1.dist-info/top_level.txt
amp_rsl_rl-1.1.1.dist-info/RECORD
