Metadata-Version: 2.4
Name: amp-rsl-rl
Version: 1.1.1
Summary: Adversarial Motion Prior (AMP) reinforcement learning extension for PPO based on RSL-RL.
Author-email: Giulio Romualdi <giulio.romualdi@iit.it>, Giuseppe L'Erario <giuseppe.lerario@iit.it>
Maintainer-email: Giulio Romualdi <giulio.romualdi@iit.it>, Giuseppe L'Erario <giuseppe.lerario@iit.it>
License-Expression: BSD-3-Clause
Project-URL: Homepage, https://github.com/ami-iit/amp-rsl-rl
Project-URL: Repository, https://github.com/ami-iit/amp-rsl-rl
Project-URL: BugTracker, https://github.com/ami-iit/amp-rsl-rl/issues
Project-URL: Changelog, https://github.com/ami-iit/amp-rsl-rl/releases
Keywords: reinforcement-learning,robotics,motion-priors,ppo
Classifier: Development Status :: 4 - Beta
Classifier: Intended Audience :: Science/Research
Classifier: Programming Language :: Python :: 3
Classifier: Programming Language :: Python :: 3.8
Classifier: Programming Language :: Python :: 3.9
Classifier: Programming Language :: Python :: 3.10
Classifier: Topic :: Scientific/Engineering :: Artificial Intelligence
Requires-Python: >=3.8
License-File: LICENSE
Requires-Dist: numpy>=1.21.0
Requires-Dist: scipy>=1.7.0
Requires-Dist: rsl-rl-lib>=3.0.0
Requires-Dist: torch>=2.6.0
Requires-Dist: tensordict>=0.7.0
Provides-Extra: examples
Requires-Dist: huggingface_hub; extra == "examples"
Dynamic: license-file
